{
  "text": [
    {
      "desc": "Moscatel Pasa\nGran Moscatel Pasa\ngran moscatel pasa vino natural de la pasa compania mata union de bodegas andaluzas, S.A.\nVino Natural de la Pasa\nvino natural de la pasa\nCompañía Mata\nUnión de Bodegas Andaluza, S.A.\ncamapnia mata union de bodegas andaluzas, S.A.\nCompania MATA; Unión de Bodegas Andaluzas, S.Á.\nCompania MATA Union de Bodegas Andaluzas, S.A.\nMálaga\nmalaga\nMalaga\nR.E. 411\nre 411",
      "bounds": [
        {
          "x": 410,
          "y": 132
        },
        {
          "x": 1759,
          "y": 132
        },
        {
          "x": 1759,
          "y": 1314
        },
        {
          "x": 410,
          "y": 1314
        }
      ]
    },
    {
      "desc": "Gran Moscatel Pasa",
      "bounds": [
        {
          "x": 410,
          "y": 132
        },
        {
          "x": 1572,
          "y": 132
        },
        {
          "x": 1572,
          "y": 1122
        },
        {
          "x": 410,
          "y": 1122
        }
      ]
    },
    {
      "desc": "gran moscatel pasa vino natural de la pasa compania mata union de bodegas andaluzas, S.A.",
      "bounds": [
        {
          "x": 410,
          "y": 132
        },
        {
          "x": 1572,
          "y": 132
        },
        {
          "x": 1572,
          "y": 1122
        },
        {
          "x": 410,
          "y": 1122
        }
      ]
    },
    {
      "desc": "Moscatel Pasa",
      "bounds": [
        {
          "x": 410,
          "y": 132
        },
        {
          "x": 1572,
          "y": 132
        },
        {
          "x": 1572,
          "y": 1122
        },
        {
          "x": 410,
          "y": 1122
        }
      ]
    },
    {
      "desc": null,
      "bounds": [
        {
          "x": 1114,
          "y": 212
        },
        {
          "x": 1365,
          "y": 212
        },
        {
          "x": 1365,
          "y": 402
        },
        {
          "x": 1114,
          "y": 402
        }
      ]
    },
    {
      "desc": null,
      "bounds": [
        {
          "x": 495,
          "y": 297
        },
        {
          "x": 1571,
          "y": 297
        },
        {
          "x": 1571,
          "y": 1174
        },
        {
          "x": 495,
          "y": 1174
        }
      ]
    },
    {
      "desc": "Vino Natural de la Pasa",
      "bounds": [
        {
          "x": 1052,
          "y": 812
        },
        {
          "x": 1759,
          "y": 812
        },
        {
          "x": 1759,
          "y": 1029
        },
        {
          "x": 1052,
          "y": 1029
        }
      ]
    },
    {
      "desc": "vino natural de la pasa",
      "bounds": [
        {
          "x": 1052,
          "y": 812
        },
        {
          "x": 1759,
          "y": 812
        },
        {
          "x": 1759,
          "y": 1029
        },
        {
          "x": 1052,
          "y": 1029
        }
      ]
    },
    {
      "desc": "Compañía Mata\nUnión de Bodegas Andaluza, S.A.",
      "bounds": [
        {
          "x": 880,
          "y": 976
        },
        {
          "x": 1739,
          "y": 976
        },
        {
          "x": 1739,
          "y": 1181
        },
        {
          "x": 880,
          "y": 1181
        }
      ]
    },
    {
      "desc": "Compania MATA Union de Bodegas Andaluzas, S.A.",
      "bounds": [
        {
          "x": 880,
          "y": 976
        },
        {
          "x": 1739,
          "y": 976
        },
        {
          "x": 1739,
          "y": 1181
        },
        {
          "x": 880,
          "y": 1181
        }
      ]
    },
    {
      "desc": "camapnia mata union de bodegas andaluzas, S.A.",
      "bounds": [
        {
          "x": 880,
          "y": 976
        },
        {
          "x": 1739,
          "y": 976
        },
        {
          "x": 1739,
          "y": 1181
        },
        {
          "x": 880,
          "y": 1181
        }
      ]
    },
    {
      "desc": "Compania MATA; Unión de Bodegas Andaluzas, S.Á.",
      "bounds": [
        {
          "x": 880,
          "y": 976
        },
        {
          "x": 1739,
          "y": 976
        },
        {
          "x": 1739,
          "y": 1181
        },
        {
          "x": 880,
          "y": 1181
        }
      ]
    },
    {
      "desc": "Malaga",
      "bounds": [
        {
          "x": 940,
          "y": 1130
        },
        {
          "x": 1592,
          "y": 1130
        },
        {
          "x": 1592,
          "y": 1238
        },
        {
          "x": 940,
          "y": 1238
        }
      ]
    },
    {
      "desc": "Málaga",
      "bounds": [
        {
          "x": 940,
          "y": 1130
        },
        {
          "x": 1592,
          "y": 1130
        },
        {
          "x": 1592,
          "y": 1238
        },
        {
          "x": 940,
          "y": 1238
        }
      ]
    },
    {
      "desc": "malaga",
      "bounds": [
        {
          "x": 940,
          "y": 1130
        },
        {
          "x": 1592,
          "y": 1130
        },
        {
          "x": 1592,
          "y": 1238
        },
        {
          "x": 940,
          "y": 1238
        }
      ]
    },
    {
      "desc": "R.E. 411",
      "bounds": [
        {
          "x": 1418,
          "y": 1190
        },
        {
          "x": 1644,
          "y": 1190
        },
        {
          "x": 1644,
          "y": 1314
        },
        {
          "x": 1418,
          "y": 1314
        }
      ]
    },
    {
      "desc": "re 411",
      "bounds": [
        {
          "x": 1418,
          "y": 1190
        },
        {
          "x": 1644,
          "y": 1190
        },
        {
          "x": 1644,
          "y": 1314
        },
        {
          "x": 1418,
          "y": 1314
        }
      ]
    }
  ],
  "image": [
    {
      "desc": "Crest",
      "bounds": [
        {
          "x": 1244,
          "y": 612
        },
        {
          "x": 1578,
          "y": 612
        },
        {
          "x": 1578,
          "y": 832
        },
        {
          "x": 1244,
          "y": 832
        }
      ]
    },
    {
      "desc": "Shield",
      "bounds": [
        {
          "x": 1244,
          "y": 612
        },
        {
          "x": 1578,
          "y": 612
        },
        {
          "x": 1578,
          "y": 832
        },
        {
          "x": 1244,
          "y": 832
        }
      ]
    },
    {
      "desc": "shield/crest",
      "bounds": [
        {
          "x": 1244,
          "y": 612
        },
        {
          "x": 1578,
          "y": 612
        },
        {
          "x": 1578,
          "y": 832
        },
        {
          "x": 1244,
          "y": 832
        }
      ]
    },
    {
      "desc": "Bunch of grapes",
      "bounds": [
        {
          "x": 444,
          "y": 163
        },
        {
          "x": 1246,
          "y": 163
        },
        {
          "x": 1246,
          "y": 1275
        },
        {
          "x": 444,
          "y": 1275
        }
      ]
    },
    {
      "desc": "Grape cluster",
      "bounds": [
        {
          "x": 444,
          "y": 163
        },
        {
          "x": 1246,
          "y": 163
        },
        {
          "x": 1246,
          "y": 1275
        },
        {
          "x": 444,
          "y": 1275
        }
      ]
    },
    {
      "desc": "grape bunch with ribbon",
      "bounds": [
        {
          "x": 444,
          "y": 163
        },
        {
          "x": 1246,
          "y": 163
        },
        {
          "x": 1246,
          "y": 1275
        },
        {
          "x": 444,
          "y": 1275
        }
      ]
    }
  ]
}
