{
  "text": [
    {
      "desc": "NATURAL FER M ENT A T O N N THE BOTTLE\nCOOKS\nA M E R I C A N\nparking Burgundy\nCONTENTS\nI PT. IO FL. OZS ALCOHOL 12% BY VOLUME\nMANUFACTURE D & BOTTLED BY\nAMERICAN. W INE CO ESTAGL. I 8.59 ST. LOUIS U. S. A.\n1942. A. w. co., LITHo IN u, s. A.\nTRADU MARK REG. U. S, PAT, OFF.\n",
      "bounds": [
        {
          "x": 474,
          "y": 367
        },
        {
          "x": 1559,
          "y": 367
        },
        {
          "x": 1559,
          "y": 1187
        },
        {
          "x": 474,
          "y": 1187
        }
      ]
    },
    {
      "desc": "NATURAL",
      "bounds": [
        {
          "x": 483,
          "y": 367
        },
        {
          "x": 727,
          "y": 367
        },
        {
          "x": 727,
          "y": 399
        },
        {
          "x": 483,
          "y": 399
        }
      ]
    },
    {
      "desc": "FER",
      "bounds": [
        {
          "x": 747,
          "y": 367
        },
        {
          "x": 837,
          "y": 367
        },
        {
          "x": 837,
          "y": 399
        },
        {
          "x": 747,
          "y": 399
        }
      ]
    },
    {
      "desc": "M",
      "bounds": [
        {
          "x": 857,
          "y": 367
        },
        {
          "x": 875,
          "y": 367
        },
        {
          "x": 875,
          "y": 399
        },
        {
          "x": 857,
          "y": 399
        }
      ]
    },
    {
      "desc": "ENT",
      "bounds": [
        {
          "x": 896,
          "y": 367
        },
        {
          "x": 979,
          "y": 367
        },
        {
          "x": 979,
          "y": 399
        },
        {
          "x": 896,
          "y": 399
        }
      ]
    },
    {
      "desc": "A",
      "bounds": [
        {
          "x": 990,
          "y": 367
        },
        {
          "x": 1012,
          "y": 367
        },
        {
          "x": 1012,
          "y": 399
        },
        {
          "x": 990,
          "y": 399
        }
      ]
    },
    {
      "desc": "T",
      "bounds": [
        {
          "x": 1024,
          "y": 368
        },
        {
          "x": 1037,
          "y": 368
        },
        {
          "x": 1037,
          "y": 394
        },
        {
          "x": 1024,
          "y": 394
        }
      ]
    },
    {
      "desc": "O",
      "bounds": [
        {
          "x": 1074,
          "y": 368
        },
        {
          "x": 1091,
          "y": 368
        },
        {
          "x": 1091,
          "y": 394
        },
        {
          "x": 1074,
          "y": 394
        }
      ]
    },
    {
      "desc": "N",
      "bounds": [
        {
          "x": 1111,
          "y": 367
        },
        {
          "x": 1128,
          "y": 367
        },
        {
          "x": 1128,
          "y": 399
        },
        {
          "x": 1111,
          "y": 399
        }
      ]
    },
    {
      "desc": "N",
      "bounds": [
        {
          "x": 1190,
          "y": 369
        },
        {
          "x": 1210,
          "y": 369
        },
        {
          "x": 1210,
          "y": 396
        },
        {
          "x": 1190,
          "y": 396
        }
      ]
    },
    {
      "desc": "THE",
      "bounds": [
        {
          "x": 1252,
          "y": 367
        },
        {
          "x": 1348,
          "y": 367
        },
        {
          "x": 1348,
          "y": 399
        },
        {
          "x": 1252,
          "y": 399
        }
      ]
    },
    {
      "desc": "BOTTLE",
      "bounds": [
        {
          "x": 1363,
          "y": 367
        },
        {
          "x": 1558,
          "y": 367
        },
        {
          "x": 1558,
          "y": 399
        },
        {
          "x": 1363,
          "y": 399
        }
      ]
    },
    {
      "desc": "COOKS",
      "bounds": [
        {
          "x": 818,
          "y": 482
        },
        {
          "x": 1247,
          "y": 463
        },
        {
          "x": 1257,
          "y": 705
        },
        {
          "x": 829,
          "y": 724
        }
      ]
    },
    {
      "desc": "A",
      "bounds": [
        {
          "x": 730,
          "y": 818
        },
        {
          "x": 776,
          "y": 818
        },
        {
          "x": 776,
          "y": 867
        },
        {
          "x": 730,
          "y": 867
        }
      ]
    },
    {
      "desc": "M",
      "bounds": [
        {
          "x": 802,
          "y": 818
        },
        {
          "x": 864,
          "y": 818
        },
        {
          "x": 864,
          "y": 867
        },
        {
          "x": 802,
          "y": 867
        }
      ]
    },
    {
      "desc": "E",
      "bounds": [
        {
          "x": 895,
          "y": 818
        },
        {
          "x": 931,
          "y": 818
        },
        {
          "x": 931,
          "y": 867
        },
        {
          "x": 895,
          "y": 867
        }
      ]
    },
    {
      "desc": "R",
      "bounds": [
        {
          "x": 968,
          "y": 818
        },
        {
          "x": 1024,
          "y": 818
        },
        {
          "x": 1024,
          "y": 867
        },
        {
          "x": 968,
          "y": 867
        }
      ]
    },
    {
      "desc": "I",
      "bounds": [
        {
          "x": 1047,
          "y": 818
        },
        {
          "x": 1083,
          "y": 818
        },
        {
          "x": 1083,
          "y": 867
        },
        {
          "x": 1047,
          "y": 867
        }
      ]
    },
    {
      "desc": "C",
      "bounds": [
        {
          "x": 1118,
          "y": 818
        },
        {
          "x": 1152,
          "y": 818
        },
        {
          "x": 1152,
          "y": 867
        },
        {
          "x": 1118,
          "y": 867
        }
      ]
    },
    {
      "desc": "A",
      "bounds": [
        {
          "x": 1179,
          "y": 818
        },
        {
          "x": 1232,
          "y": 818
        },
        {
          "x": 1232,
          "y": 867
        },
        {
          "x": 1179,
          "y": 867
        }
      ]
    },
    {
      "desc": "N",
      "bounds": [
        {
          "x": 1266,
          "y": 818
        },
        {
          "x": 1299,
          "y": 818
        },
        {
          "x": 1299,
          "y": 867
        },
        {
          "x": 1266,
          "y": 867
        }
      ]
    },
    {
      "desc": "parking",
      "bounds": [
        {
          "x": 700,
          "y": 890
        },
        {
          "x": 983,
          "y": 890
        },
        {
          "x": 983,
          "y": 984
        },
        {
          "x": 700,
          "y": 984
        }
      ]
    },
    {
      "desc": "Burgundy",
      "bounds": [
        {
          "x": 1059,
          "y": 873
        },
        {
          "x": 1384,
          "y": 873
        },
        {
          "x": 1384,
          "y": 982
        },
        {
          "x": 1059,
          "y": 982
        }
      ]
    },
    {
      "desc": "CONTENTS",
      "bounds": [
        {
          "x": 474,
          "y": 1032
        },
        {
          "x": 661,
          "y": 1032
        },
        {
          "x": 661,
          "y": 1059
        },
        {
          "x": 474,
          "y": 1059
        }
      ]
    },
    {
      "desc": "I",
      "bounds": [
        {
          "x": 685,
          "y": 1031
        },
        {
          "x": 697,
          "y": 1031
        },
        {
          "x": 697,
          "y": 1064
        },
        {
          "x": 685,
          "y": 1064
        }
      ]
    },
    {
      "desc": "PT.",
      "bounds": [
        {
          "x": 717,
          "y": 1031
        },
        {
          "x": 766,
          "y": 1031
        },
        {
          "x": 766,
          "y": 1064
        },
        {
          "x": 717,
          "y": 1064
        }
      ]
    },
    {
      "desc": "IO",
      "bounds": [
        {
          "x": 777,
          "y": 1031
        },
        {
          "x": 815,
          "y": 1031
        },
        {
          "x": 815,
          "y": 1064
        },
        {
          "x": 777,
          "y": 1064
        }
      ]
    },
    {
      "desc": "FL.",
      "bounds": [
        {
          "x": 834,
          "y": 1031
        },
        {
          "x": 887,
          "y": 1031
        },
        {
          "x": 887,
          "y": 1064
        },
        {
          "x": 834,
          "y": 1064
        }
      ]
    },
    {
      "desc": "OZS",
      "bounds": [
        {
          "x": 898,
          "y": 1031
        },
        {
          "x": 969,
          "y": 1031
        },
        {
          "x": 969,
          "y": 1064
        },
        {
          "x": 898,
          "y": 1064
        }
      ]
    },
    {
      "desc": "ALCOHOL",
      "bounds": [
        {
          "x": 1037,
          "y": 1032
        },
        {
          "x": 1212,
          "y": 1033
        },
        {
          "x": 1212,
          "y": 1066
        },
        {
          "x": 1037,
          "y": 1065
        }
      ]
    },
    {
      "desc": "12%",
      "bounds": [
        {
          "x": 1228,
          "y": 1032
        },
        {
          "x": 1307,
          "y": 1032
        },
        {
          "x": 1307,
          "y": 1065
        },
        {
          "x": 1228,
          "y": 1065
        }
      ]
    },
    {
      "desc": "BY",
      "bounds": [
        {
          "x": 1329,
          "y": 1033
        },
        {
          "x": 1369,
          "y": 1033
        },
        {
          "x": 1369,
          "y": 1066
        },
        {
          "x": 1329,
          "y": 1066
        }
      ]
    },
    {
      "desc": "VOLUME",
      "bounds": [
        {
          "x": 1389,
          "y": 1033
        },
        {
          "x": 1547,
          "y": 1033
        },
        {
          "x": 1547,
          "y": 1066
        },
        {
          "x": 1389,
          "y": 1066
        }
      ]
    },
    {
      "desc": "MANUFACTURE",
      "bounds": [
        {
          "x": 785,
          "y": 1098
        },
        {
          "x": 992,
          "y": 1098
        },
        {
          "x": 992,
          "y": 1120
        },
        {
          "x": 785,
          "y": 1120
        }
      ]
    },
    {
      "desc": "D",
      "bounds": [
        {
          "x": 997,
          "y": 1098
        },
        {
          "x": 1013,
          "y": 1098
        },
        {
          "x": 1013,
          "y": 1120
        },
        {
          "x": 997,
          "y": 1120
        }
      ]
    },
    {
      "desc": "&",
      "bounds": [
        {
          "x": 1030,
          "y": 1098
        },
        {
          "x": 1049,
          "y": 1098
        },
        {
          "x": 1049,
          "y": 1120
        },
        {
          "x": 1030,
          "y": 1120
        }
      ]
    },
    {
      "desc": "BOTTLED",
      "bounds": [
        {
          "x": 1066,
          "y": 1098
        },
        {
          "x": 1187,
          "y": 1098
        },
        {
          "x": 1187,
          "y": 1120
        },
        {
          "x": 1066,
          "y": 1120
        }
      ]
    },
    {
      "desc": "BY",
      "bounds": [
        {
          "x": 1202,
          "y": 1098
        },
        {
          "x": 1239,
          "y": 1098
        },
        {
          "x": 1239,
          "y": 1120
        },
        {
          "x": 1202,
          "y": 1120
        }
      ]
    },
    {
      "desc": "AMERICAN.",
      "bounds": [
        {
          "x": 483,
          "y": 1124
        },
        {
          "x": 720,
          "y": 1125
        },
        {
          "x": 720,
          "y": 1157
        },
        {
          "x": 483,
          "y": 1156
        }
      ]
    },
    {
      "desc": "W",
      "bounds": [
        {
          "x": 742,
          "y": 1125
        },
        {
          "x": 762,
          "y": 1125
        },
        {
          "x": 762,
          "y": 1157
        },
        {
          "x": 742,
          "y": 1157
        }
      ]
    },
    {
      "desc": "INE",
      "bounds": [
        {
          "x": 770,
          "y": 1125
        },
        {
          "x": 836,
          "y": 1125
        },
        {
          "x": 836,
          "y": 1157
        },
        {
          "x": 770,
          "y": 1157
        }
      ]
    },
    {
      "desc": "CO",
      "bounds": [
        {
          "x": 856,
          "y": 1125
        },
        {
          "x": 896,
          "y": 1125
        },
        {
          "x": 896,
          "y": 1157
        },
        {
          "x": 856,
          "y": 1157
        }
      ]
    },
    {
      "desc": "ESTAGL.",
      "bounds": [
        {
          "x": 949,
          "y": 1125
        },
        {
          "x": 1066,
          "y": 1125
        },
        {
          "x": 1066,
          "y": 1157
        },
        {
          "x": 949,
          "y": 1157
        }
      ]
    },
    {
      "desc": "I",
      "bounds": [
        {
          "x": 1079,
          "y": 1126
        },
        {
          "x": 1088,
          "y": 1126
        },
        {
          "x": 1088,
          "y": 1158
        },
        {
          "x": 1079,
          "y": 1158
        }
      ]
    },
    {
      "desc": "8.59",
      "bounds": [
        {
          "x": 1099,
          "y": 1126
        },
        {
          "x": 1172,
          "y": 1126
        },
        {
          "x": 1172,
          "y": 1158
        },
        {
          "x": 1099,
          "y": 1158
        }
      ]
    },
    {
      "desc": "ST.",
      "bounds": [
        {
          "x": 1225,
          "y": 1126
        },
        {
          "x": 1277,
          "y": 1126
        },
        {
          "x": 1277,
          "y": 1158
        },
        {
          "x": 1225,
          "y": 1158
        }
      ]
    },
    {
      "desc": "LOUIS",
      "bounds": [
        {
          "x": 1286,
          "y": 1126
        },
        {
          "x": 1406,
          "y": 1126
        },
        {
          "x": 1406,
          "y": 1158
        },
        {
          "x": 1286,
          "y": 1158
        }
      ]
    },
    {
      "desc": "U.",
      "bounds": [
        {
          "x": 1453,
          "y": 1127
        },
        {
          "x": 1479,
          "y": 1127
        },
        {
          "x": 1479,
          "y": 1159
        },
        {
          "x": 1453,
          "y": 1159
        }
      ]
    },
    {
      "desc": "S.",
      "bounds": [
        {
          "x": 1488,
          "y": 1127
        },
        {
          "x": 1516,
          "y": 1127
        },
        {
          "x": 1516,
          "y": 1159
        },
        {
          "x": 1488,
          "y": 1159
        }
      ]
    },
    {
      "desc": "A.",
      "bounds": [
        {
          "x": 1524,
          "y": 1127
        },
        {
          "x": 1559,
          "y": 1127
        },
        {
          "x": 1559,
          "y": 1159
        },
        {
          "x": 1524,
          "y": 1159
        }
      ]
    },
    {
      "desc": "1942.",
      "bounds": [
        {
          "x": 504,
          "y": 1158
        },
        {
          "x": 549,
          "y": 1159
        },
        {
          "x": 549,
          "y": 1184
        },
        {
          "x": 504,
          "y": 1183
        }
      ]
    },
    {
      "desc": "A.",
      "bounds": [
        {
          "x": 552,
          "y": 1159
        },
        {
          "x": 571,
          "y": 1159
        },
        {
          "x": 571,
          "y": 1184
        },
        {
          "x": 552,
          "y": 1184
        }
      ]
    },
    {
      "desc": "w.",
      "bounds": [
        {
          "x": 581,
          "y": 1159
        },
        {
          "x": 597,
          "y": 1159
        },
        {
          "x": 597,
          "y": 1184
        },
        {
          "x": 581,
          "y": 1184
        }
      ]
    },
    {
      "desc": "co.,",
      "bounds": [
        {
          "x": 604,
          "y": 1160
        },
        {
          "x": 645,
          "y": 1160
        },
        {
          "x": 645,
          "y": 1185
        },
        {
          "x": 604,
          "y": 1185
        }
      ]
    },
    {
      "desc": "LITHo",
      "bounds": [
        {
          "x": 651,
          "y": 1160
        },
        {
          "x": 703,
          "y": 1161
        },
        {
          "x": 703,
          "y": 1186
        },
        {
          "x": 651,
          "y": 1185
        }
      ]
    },
    {
      "desc": "IN",
      "bounds": [
        {
          "x": 714,
          "y": 1161
        },
        {
          "x": 734,
          "y": 1161
        },
        {
          "x": 734,
          "y": 1186
        },
        {
          "x": 714,
          "y": 1186
        }
      ]
    },
    {
      "desc": "u,",
      "bounds": [
        {
          "x": 744,
          "y": 1161
        },
        {
          "x": 759,
          "y": 1161
        },
        {
          "x": 759,
          "y": 1186
        },
        {
          "x": 744,
          "y": 1186
        }
      ]
    },
    {
      "desc": "s.",
      "bounds": [
        {
          "x": 764,
          "y": 1162
        },
        {
          "x": 781,
          "y": 1162
        },
        {
          "x": 781,
          "y": 1187
        },
        {
          "x": 764,
          "y": 1187
        }
      ]
    },
    {
      "desc": "A.",
      "bounds": [
        {
          "x": 787,
          "y": 1162
        },
        {
          "x": 807,
          "y": 1162
        },
        {
          "x": 807,
          "y": 1187
        },
        {
          "x": 787,
          "y": 1187
        }
      ]
    },
    {
      "desc": "TRADU",
      "bounds": [
        {
          "x": 1215,
          "y": 1168
        },
        {
          "x": 1279,
          "y": 1168
        },
        {
          "x": 1279,
          "y": 1184
        },
        {
          "x": 1215,
          "y": 1184
        }
      ]
    },
    {
      "desc": "MARK",
      "bounds": [
        {
          "x": 1291,
          "y": 1168
        },
        {
          "x": 1343,
          "y": 1168
        },
        {
          "x": 1343,
          "y": 1184
        },
        {
          "x": 1291,
          "y": 1184
        }
      ]
    },
    {
      "desc": "REG.",
      "bounds": [
        {
          "x": 1352,
          "y": 1168
        },
        {
          "x": 1397,
          "y": 1168
        },
        {
          "x": 1397,
          "y": 1184
        },
        {
          "x": 1352,
          "y": 1184
        }
      ]
    },
    {
      "desc": "U.",
      "bounds": [
        {
          "x": 1407,
          "y": 1168
        },
        {
          "x": 1423,
          "y": 1168
        },
        {
          "x": 1423,
          "y": 1184
        },
        {
          "x": 1407,
          "y": 1184
        }
      ]
    },
    {
      "desc": "S,",
      "bounds": [
        {
          "x": 1432,
          "y": 1168
        },
        {
          "x": 1448,
          "y": 1168
        },
        {
          "x": 1448,
          "y": 1184
        },
        {
          "x": 1432,
          "y": 1184
        }
      ]
    },
    {
      "desc": "PAT,",
      "bounds": [
        {
          "x": 1455,
          "y": 1168
        },
        {
          "x": 1497,
          "y": 1168
        },
        {
          "x": 1497,
          "y": 1184
        },
        {
          "x": 1455,
          "y": 1184
        }
      ]
    },
    {
      "desc": "OFF.",
      "bounds": [
        {
          "x": 1503,
          "y": 1168
        },
        {
          "x": 1545,
          "y": 1168
        },
        {
          "x": 1545,
          "y": 1184
        },
        {
          "x": 1503,
          "y": 1184
        }
      ]
    }
  ],
  "logos": [],
  "errors": [],
  "labels": [
    {
      "mid": "/m/013y0j",
      "desc": "organ",
      "score": 65.407646
    },
    {
      "mid": "/m/014sv8",
      "desc": "eye",
      "score": 61.59713300000001
    },
    {
      "mid": "/m/05c0n6k",
      "desc": "label",
      "score": 59.691768999999994
    }
  ],
  "landmarks": [],
  "properties": {
    "colors": [
      {
        "hex": "0f0905",
        "red": 15,
        "blue": 5,
        "green": 9,
        "score": 44.770782999999994,
        "coverage": 25
      },
      {
        "hex": "d0bf9c",
        "red": 208,
        "blue": 156,
        "green": 191,
        "score": 10.972194,
        "coverage": 2.1266667
      },
      {
        "hex": "827559",
        "red": 130,
        "blue": 89,
        "green": 117,
        "score": 6.4549439,
        "coverage": 1.0133334
      },
      {
        "hex": "aa9b7b",
        "red": 170,
        "blue": 123,
        "green": 155,
        "score": 6.3888244,
        "coverage": 0.62
      },
      {
        "hex": "38322c",
        "red": 56,
        "blue": 44,
        "green": 50,
        "score": 5.5341624,
        "coverage": 2.6133334
      },
      {
        "hex": "39301c",
        "red": 57,
        "blue": 28,
        "green": 48,
        "score": 4.6843689,
        "coverage": 0.9333332999999999
      },
      {
        "hex": "5f5238",
        "red": 95,
        "blue": 56,
        "green": 82,
        "score": 4.5789529,
        "coverage": 0.5133333200000001
      },
      {
        "hex": "241a06",
        "red": 36,
        "blue": 6,
        "green": 26,
        "score": 4.475359999999999,
        "coverage": 1
      },
      {
        "hex": "5a534c",
        "red": 90,
        "blue": 76,
        "green": 83,
        "score": 3.0506413,
        "coverage": 1.44
      },
      {
        "hex": "645027",
        "red": 100,
        "blue": 39,
        "green": 80,
        "score": 2.0279776,
        "coverage": 0.1
      }
    ]
  }
}
